bibliography_organizer/Bibliography.py
bibliography_organizer/Bibtex.py
bibliography_organizer/Document.py
bibliography_organizer/Entry.py
bibliography_organizer/Index.py
bibliography_organizer/Reader.py
bibliography_organizer/Status.py
bibliography_organizer/__init__.py
bibliography_organizer/scripts/main.py
bibliography_organizer_sebastian_achim_mueller-1.1.4.dist-info/LICENSE
bibliography_organizer_sebastian_achim_mueller-1.1.4.dist-info/METADATA
bibliography_organizer_sebastian_achim_mueller-1.1.4.dist-info/WHEEL
bibliography_organizer_sebastian_achim_mueller-1.1.4.dist-info/entry_points.txt
bibliography_organizer_sebastian_achim_mueller-1.1.4.dist-info/top_level.txt
bibliography_organizer_sebastian_achim_mueller-1.1.4.dist-info/RECORD
