Metadata-Version: 2.1
Name: bibliography-organizer-sebastian-achim-mueller
Version: 1.1.4
Summary: Organize your bibliography
Home-page: https://github.com/relleums/bibliography_organizer
Author: Sebastian Achim Mueller
Author-email: sebastian-achim.mueller@mpi-hd.mpg.de
License: MIT
Project-URL: Bug Tracker, https://github.com/relleums/bibliography_organizer/issues
Platform: UNKNOWN
Classifier: Programming Language :: Python :: 3
Classifier: License :: OSI Approved :: MIT License
Classifier: Operating System :: OS Independent
Classifier: Natural Language :: English
Classifier: Intended Audience :: Science/Research
Requires-Python: >=3
Requires-Dist: minimal-bibtex-io-sebastian-achim-mueller
Requires-Dist: pytesseract
Requires-Dist: whoosh
